bidding_properties_pkg/__init__.py
bidding_properties_pkg/bidding_properties.py
Bidmanger_pkg-0.0.2.dist-info/METADATA
Bidmanger_pkg-0.0.2.dist-info/WHEEL
Bidmanger_pkg-0.0.2.dist-info/top_level.txt
Bidmanger_pkg-0.0.2.dist-info/RECORD
