Metadata-Version: 2.1
Name: Bidmanger-pkg
Version: 0.0.2
Summary: A small example package
Home-page: https://github.com/pypa/sampleproject
Author: Rahul Shirsat
Author-email: rahulshirsat9156@gmail.com
Classifier: Programming Language :: Python :: 3
Classifier: License :: OSI Approved :: MIT License
Classifier: Operating System :: OS Independent
Requires-Python: >=3.6
Requires-Dist: boto3
